arcadedb_embedded/__init__.py
arcadedb_embedded/_version.py
arcadedb_embedded/core.py
arcadedb_embedded/exceptions.py
arcadedb_embedded/importer.py
arcadedb_embedded/jvm.py
arcadedb_embedded/results.py
arcadedb_embedded/server.py
arcadedb_embedded/transactions.py
arcadedb_embedded/vector.py
arcadedb_embedded/jars/HdrHistogram-2.2.2.jar
arcadedb_embedded/jars/LatencyUtils-2.0.3.jar
arcadedb_embedded/jars/arcadedb-console-25.9.1.jar
arcadedb_embedded/jars/arcadedb-engine-25.9.1.jar
arcadedb_embedded/jars/arcadedb-grpcw-25.9.1-shaded.jar
arcadedb_embedded/jars/arcadedb-integration-25.9.1.jar
arcadedb_embedded/jars/arcadedb-metrics-25.9.1.jar
arcadedb_embedded/jars/arcadedb-network-25.9.1.jar
arcadedb_embedded/jars/arcadedb-postgresw-25.9.1-shaded.jar
arcadedb_embedded/jars/arcadedb-server-25.9.1.jar
arcadedb_embedded/jars/collections-24.2.2.jar
arcadedb_embedded/jars/commons-lang3-3.18.0.jar
arcadedb_embedded/jars/disruptor-1.2.21.jar
arcadedb_embedded/jars/eclipse-collections-9.2.0.jar
arcadedb_embedded/jars/eclipse-collections-api-9.2.0.jar
arcadedb_embedded/jars/error_prone_annotations-2.41.0.jar
arcadedb_embedded/jars/graal-sdk-24.2.2.jar
arcadedb_embedded/jars/gson-2.13.2.jar
arcadedb_embedded/jars/hnswlib-core-1.1.0.jar
arcadedb_embedded/jars/icu4j-24.2.2.jar
arcadedb_embedded/jars/jackson-annotations-2.19.2.jar
arcadedb_embedded/jars/jackson-core-2.19.2.jar
arcadedb_embedded/jars/jackson-databind-2.19.2.jar
arcadedb_embedded/jars/jackson-dataformat-yaml-2.19.2.jar
arcadedb_embedded/jars/jackson-datatype-jsr310-2.19.2.jar
arcadedb_embedded/jars/jakarta.activation-api-1.2.2.jar
arcadedb_embedded/jars/jakarta.validation-api-2.0.2.jar
arcadedb_embedded/jars/jakarta.xml.bind-api-2.3.3.jar
arcadedb_embedded/jars/jboss-logging-3.4.3.Final.jar
arcadedb_embedded/jars/jboss-threads-3.7.0.Final.jar
arcadedb_embedded/jars/jline-native-3.30.6.jar
arcadedb_embedded/jars/jline-reader-3.30.6.jar
arcadedb_embedded/jars/jline-terminal-3.30.6.jar
arcadedb_embedded_headless-25.9.1.3.dist-info/METADATA
arcadedb_embedded_headless-25.9.1.3.dist-info/WHEEL
arcadedb_embedded_headless-25.9.1.3.dist-info/top_level.txt
arcadedb_embedded_headless-25.9.1.3.dist-info/RECORD
